LEDDimmerServer/DimmerBackend.py
LEDDimmerServer/HTTPHandler.py
LEDDimmerServer/LEDDimmer.py
LEDDimmerServer/__init__.py
LEDDimmerServer/__main__.py
LEDDimmerServer/__version__.py
LEDDimmerServer/color.py
LEDDimmerServer/utc.py
LEDDimmerServer/utils.py
leddimmerserver-0.1.3.dev0.dist-info/METADATA
leddimmerserver-0.1.3.dev0.dist-info/WHEEL
leddimmerserver-0.1.3.dev0.dist-info/top_level.txt
leddimmerserver-0.1.3.dev0.dist-info/RECORD
