Metadata-Version: 2.4
Name: leddimmerserver
Version: 0.1.3.dev0
Summary: A server for controlling LED dimmers
Author: terminator
Author-email: terminator <the.terminator.ger@gmail.com>
License-Expression: MIT
Requires-Python: >=3.8
Requires-Dist: gpiozero
Requires-Dist: astral
Requires-Dist: pytz
Requires-Dist: requests
Requires-Dist: simplejson
Dynamic: author
Dynamic: requires-dist
